[{"backer": "Jason Ernst", "project_data": {"campaign": {"story": "", "risks": "", "env": "", "creator_bio": ""}, "support": [], "updates": [{"status": []}], "comment_no": 34, "projec_url": "https://www.kickstarter.com/projects/hypershop/hyperjuice-worlds-most-powerful-usb-c-battery-pack", "project_name": "HyperJuice: World's Most Powerful USB-C Battery Pack"}}, {"backer": "Jason Ernst", "project_data": {"campaign": {"story": "", "risks": "", "env": "", "creator_bio": ""}, "support": [], "updates": [{"status": []}], "comment_no": 34, "projec_url": "https://www.kickstarter.com/projects/xdroid/xdroid-the-first-truly-gamified-remote-controlled", "project_name": "xDroid \u2013 The first truly gamified RC car (Canceled)"}}, {"backer": "Jason Ernst", "project_data": {"campaign": {"story": "", "risks": "", "env": "", "creator_bio": ""}, "support": [], "updates": [{"status": []}], "comment_no": 34, "projec_url": "https://www.kickstarter.com/projects/625059603/the-micro-wallet-doing-more-with-less", "project_name": "The Micro Wallet - Doing more with less"}}, {"backer": "Jason Ernst", "project_data": {"campaign": {"story": "", "risks": "", "env": "", "creator_bio": ""}, "support": [], "updates": [{"status": []}], "comment_no": 34, "projec_url": "https://www.kickstarter.com/projects/421938988/deskview-the-worlds-first-window-mounted-standing", "project_name": "Deskview: The World's First Window-Mounted Standing Desk"}}, {"backer": "Jason Ernst", "project_data": {"campaign": {"story": "", "risks": "", "env": "", "creator_bio": ""}, "support": [], "updates": [{"status": []}], "comment_no": 34, "projec_url": "https://www.kickstarter.com/projects/minimonkey/monkey-light-the-most-effective-way-to-be-seen-on", "project_name": "Monkey Light Automatic: our best bike lights yet"}}, {"backer": "Jason Ernst", "project_data": {"campaign": {"story": "", "risks": "", "env": "", "creator_bio": ""}, "support": [], "updates": [{"status": []}], "comment_no": 34, "projec_url": "https://www.kickstarter.com/projects/elanlee/bears-vs-babies-a-card-game", "project_name": "Bears vs Babies - A Card Game"}}, {"backer": "Jason Ernst", "project_data": {"campaign": {"story": "", "risks": "", "env": "", "creator_bio": ""}, "support": [], "updates": [{"status": []}], "comment_no": 34, "projec_url": "https://www.kickstarter.com/projects/961196631/the-spiral-of-containment-rapes-aftermath", "project_name": "- The Spiral of Containment: Rape's Aftermath -"}}, {"backer": "Jason Ernst", "project_data": {"campaign": {"story": "", "risks": "", "env": "", "creator_bio": ""}, "support": [], "updates": [{"status": []}], "comment_no": 34, "projec_url": "https://www.kickstarter.com/projects/byclewithme/bycle", "project_name": "Bycle \u2014 iPhone bike mount+app that integrates map+video."}}, {"backer": "Jason Ernst", "project_data": {"campaign": {"story": "", "risks": "", "env": "", "creator_bio": ""}, "support": [], "updates": [{"status": []}], "comment_no": 34, "projec_url": "https://www.kickstarter.com/projects/333155164/carv-the-worlds-first-wearable-that-helps-you-ski", "project_name": "CARV: The world\u2019s first wearable that helps you ski better!"}}, {"backer": "Jason Ernst", "project_data": {"campaign": {"story": "", "risks": "", "env": "", "creator_bio": ""}, "support": [], "updates": [{"status": []}], "comment_no": 34, "projec_url": "https://www.kickstarter.com/projects/grasp/grasp-quick-release-bike-lock-with-fingerprint-rec", "project_name": "Grasp - Bicycle Lock with Fingerprint Recognition (Canceled)"}}, {"backer": "Jason Ernst", "project_data": {"campaign": {"story": "", "risks": "", "env": "", "creator_bio": ""}, "support": [], "updates": [{"status": []}], "comment_no": 34, "projec_url": "https://www.kickstarter.com/projects/uhwk/the-wearable-camera-for-athletes", "project_name": "The Wearable Camera for Athletes"}}, {"backer": "Jason Ernst", "project_data": {"campaign": {"story": "", "risks": "", "env": "", "creator_bio": ""}, "support": [], "updates": [{"status": []}], "comment_no": 34, "projec_url": "https://www.kickstarter.com/projects/991279259/sunny-side-up-eggs-cat-egg-molds", "project_name": "Sunny Side Up Eggs - Cat Fried Egg Mold"}}, {"backer": "Jason Ernst", "project_data": {"campaign": {"story": "", "risks": "", "env": "", "creator_bio": ""}, "support": [], "updates": [{"status": []}], "comment_no": 34, "projec_url": "https://www.kickstarter.com/projects/pozyx/pozyx-accurate-indoor-positioning-for-arduino", "project_name": "Pozyx: accurate indoor positioning for Arduino"}}, {"backer": "Jason Ernst", "project_data": {"campaign": {"story": "", "risks": "", "env": "", "creator_bio": ""}, "support": [], "updates": [{"status": []}], "comment_no": 34, "projec_url": "https://www.kickstarter.com/projects/bartesian/bartesian-the-first-capsule-cocktail-machine", "project_name": "Bartesian: the Ultimate Home Cocktail Machine"}}, {"backer": "Jason Ernst", "project_data": {"campaign": {"story": "", "risks": "", "env": "", "creator_bio": ""}, "support": [], "updates": [{"status": []}], "comment_no": 34, "projec_url": "https://www.kickstarter.com/projects/mosaic3d/the-palette-3d-printing-evolved", "project_name": "The Palette: 3D Printing Evolved"}}, {"backer": "Jason Ernst", "project_data": {"campaign": {"story": "", "risks": "", "env": "", "creator_bio": ""}, "support": [], "updates": [{"status": []}], "comment_no": 34, "projec_url": "https://www.kickstarter.com/projects/voltera/voltera-your-circuit-board-prototyping-machine", "project_name": "Voltera:  Your Circuit Board Prototyping Machine"}}]