[{"backer": "Katherine Pan", "project_data": {"campaign": {"story": "", "risks": "", "env": "", "creator_bio": ""}, "support": [], "updates": [{"status": []}], "comment_no": 4, "projec_url": "https://www.kickstarter.com/projects/americanrestaurant/american-restaurant-book", "project_name": "American Restaurant Book"}}, {"backer": "Katherine Pan", "project_data": {"campaign": {"story": "", "risks": "", "env": "", "creator_bio": ""}, "support": [], "updates": [{"status": []}], "comment_no": 4, "projec_url": "https://www.kickstarter.com/projects/terraplanter/terra-planter-the-inside-out-hydroponic-planter-pot", "project_name": "terraplanter - visibly follow the journey from seed to plant"}}, {"backer": "Katherine Pan", "project_data": {"campaign": {"story": "", "risks": "", "env": "", "creator_bio": ""}, "support": [], "updates": [{"status": []}], "comment_no": 4, "projec_url": "https://www.kickstarter.com/projects/saarimz/redacted-clothing", "project_name": "[[REDACTED]] Clothing"}}, {"backer": "Katherine Pan", "project_data": {"campaign": {"story": "", "risks": "", "env": "", "creator_bio": ""}, "support": [], "updates": [{"status": []}], "comment_no": 4, "projec_url": "https://www.kickstarter.com/projects/bethanysum/deepmay-tech-bootcamping", "project_name": "DEEPMAY: tech bootcamping"}}, {"backer": "Katherine Pan", "project_data": {"campaign": {"story": "", "risks": "", "env": "", "creator_bio": ""}, "support": [], "updates": [{"status": []}], "comment_no": 4, "projec_url": "https://www.kickstarter.com/projects/bigunicorn/antennae-a-sculptural-shrine-to-the-human-imaginat", "project_name": "Antennae: A Sculptural Shrine to the Human Imagination"}}, {"backer": "Katherine Pan", "project_data": {"campaign": {"story": "", "risks": "", "env": "", "creator_bio": ""}, "support": [], "updates": [{"status": []}], "comment_no": 4, "projec_url": "https://www.kickstarter.com/projects/showgirlsdoc/goddess-the-fall-and-rise-of-showgirls", "project_name": "GODDESS: The Fall and Rise of \"Showgirls\""}}, {"backer": "Katherine Pan", "project_data": {"campaign": {"story": "", "risks": "", "env": "", "creator_bio": ""}, "support": [], "updates": [{"status": []}], "comment_no": 4, "projec_url": "https://www.kickstarter.com/projects/alfie23/100-photos-of-queens", "project_name": "100 photos of Queens"}}, {"backer": "Katherine Pan", "project_data": {"campaign": {"story": "", "risks": "", "env": "", "creator_bio": ""}, "support": [], "updates": [{"status": []}], "comment_no": 4, "projec_url": "https://www.kickstarter.com/projects/dragqueenhotsauce/meet-the-first-drag-queen-hot-sauce", "project_name": "Help the First Drag Queen Hot Sauce!"}}, {"backer": "Katherine Pan", "project_data": {"campaign": {"story": "", "risks": "", "env": "", "creator_bio": ""}, "support": [], "updates": [{"status": []}], "comment_no": 4, "projec_url": "https://www.kickstarter.com/projects/1040397542/hand-crafted-vulva-and-nipple-incense-holders", "project_name": "Hand-Crafted Vulva and Nipple Incense Holders!"}}, {"backer": "Katherine Pan", "project_data": {"campaign": {"story": "", "risks": "", "env": "", "creator_bio": ""}, "support": [], "updates": [{"status": []}], "comment_no": 4, "projec_url": "https://www.kickstarter.com/projects/pilotstudios/always-punch-nazis", "project_name": "Always Punch Nazis"}}, {"backer": "Katherine Pan", "project_data": {"campaign": {"story": "", "risks": "", "env": "", "creator_bio": ""}, "support": [], "updates": [{"status": []}], "comment_no": 4, "projec_url": "https://www.kickstarter.com/projects/flybyjing/sichuan-chili-crisp-deep-flavor-to-power-your-food", "project_name": "SICHUAN CHILI CRISP - Deep Flavor to Power Your Food"}}, {"backer": "Katherine Pan", "project_data": {"campaign": {"story": "", "risks": "", "env": "", "creator_bio": ""}, "support": [], "updates": [{"status": []}], "comment_no": 4, "projec_url": "https://www.kickstarter.com/projects/jdlv/make-100-supernachobowl", "project_name": "Make 100: #SuperNachoBowl"}}, {"backer": "Katherine Pan", "project_data": {"campaign": {"story": "", "risks": "", "env": "", "creator_bio": ""}, "support": [], "updates": [{"status": []}], "comment_no": 4, "projec_url": "https://www.kickstarter.com/projects/1971131677/a-year-undercover-inside-the-alt-right", "project_name": "A year undercover inside the alt-right"}}, {"backer": "Katherine Pan", "project_data": {"campaign": {"story": "", "risks": "", "env": "", "creator_bio": ""}, "support": [], "updates": [{"status": []}], "comment_no": 4, "projec_url": "https://www.kickstarter.com/projects/letspainttv/make-paint-100-palm-trees", "project_name": "Make (Paint) 100 Palm Trees"}}, {"backer": "Katherine Pan", "project_data": {"campaign": {"story": "", "risks": "", "env": "", "creator_bio": ""}, "support": [], "updates": [{"status": []}], "comment_no": 4, "projec_url": "https://www.kickstarter.com/projects/thedada/the-dada-zen-fidget-art-bot-non-toy-now-youre-an-a", "project_name": "The dADa | ZEN fidget | ART bot | NON toy"}}, {"backer": "Katherine Pan", "project_data": {"campaign": {"story": "", "risks": "", "env": "", "creator_bio": ""}, "support": [], "updates": [{"status": []}], "comment_no": 4, "projec_url": "https://www.kickstarter.com/projects/rumur/the-meadow-a-photo-book", "project_name": "The Meadow: A Photo Book"}}, {"backer": "Katherine Pan", "project_data": {"campaign": {"story": "", "risks": "", "env": "", "creator_bio": ""}, "support": [], "updates": [{"status": []}], "comment_no": 4, "projec_url": "https://www.kickstarter.com/projects/998384875/mexico-creates-pottery", "project_name": "Mexico Creates Pottery"}}, {"backer": "Katherine Pan", "project_data": {"campaign": {"story": "", "risks": "", "env": "", "creator_bio": ""}, "support": [], "updates": [{"status": []}], "comment_no": 4, "projec_url": "https://www.kickstarter.com/projects/2142897608/hello-tomorrow", "project_name": "HELLO TOMORROW"}}, {"backer": "Katherine Pan", "project_data": {"campaign": {"story": "", "risks": "", "env": "", "creator_bio": ""}, "support": [], "updates": [{"status": []}], "comment_no": 4, "projec_url": "https://www.kickstarter.com/projects/coppercanyonpress/oceanic-poetry-beauty-with-copper-canyon-press", "project_name": "OCEANIC: Poetry + Beauty with Copper Canyon Press"}}, {"backer": "Katherine Pan", "project_data": {"campaign": {"story": "", "risks": "", "env": "", "creator_bio": ""}, "support": [], "updates": [{"status": []}], "comment_no": 4, "projec_url": "https://www.kickstarter.com/projects/90878997/ada-a-short-film-by-eleanore-pienta", "project_name": "ADA a short film by Eleanore Pienta"}}, {"backer": "Katherine Pan", "project_data": {"campaign": {"story": "", "risks": "", "env": "", "creator_bio": ""}, "support": [], "updates": [{"status": []}], "comment_no": 4, "projec_url": "https://www.kickstarter.com/projects/1022321138/geometric-painting-commissions", "project_name": "Geometric Painting Commissions"}}, {"backer": "Katherine Pan", "project_data": {"campaign": {"story": "", "risks": "", "env": "", "creator_bio": ""}, "support": [], "updates": [{"status": []}], "comment_no": 4, "projec_url": "https://www.kickstarter.com/projects/486654385/paper-profile-silhouette-commissions", "project_name": "Paper Profile - Silhouette Commissions"}}, {"backer": "Katherine Pan", "project_data": {"campaign": {"story": "", "risks": "", "env": "", "creator_bio": ""}, "support": [], "updates": [{"status": []}], "comment_no": 4, "projec_url": "https://www.kickstarter.com/projects/timswindle/lickety-spin-make-your-own-candy-fidget-spinner-ki", "project_name": "Lickety Spin - Make Your Own Candy Fidget Spinner Kit"}}, {"backer": "Katherine Pan", "project_data": {"campaign": {"story": "", "risks": "", "env": "", "creator_bio": ""}, "support": [], "updates": [{"status": []}], "comment_no": 4, "projec_url": "https://www.kickstarter.com/projects/1477302345/qoobo", "project_name": "Qoobo : A pillow with a wagging tail"}}, {"backer": "Katherine Pan", "project_data": {"campaign": {"story": "", "risks": "", "env": "", "creator_bio": ""}, "support": [], "updates": [{"status": []}], "comment_no": 4, "projec_url": "https://www.kickstarter.com/projects/1524990961/hardboiled-magic-the-memes-from-hell", "project_name": "Hardboiled Magic: The Memes From Hell"}}, {"backer": "Katherine Pan", "project_data": {"campaign": {"story": "", "risks": "", "env": "", "creator_bio": ""}, "support": [], "updates": [{"status": []}], "comment_no": 4, "projec_url": "https://www.kickstarter.com/projects/410002714/give-me-more", "project_name": "Give Me More"}}, {"backer": "Katherine Pan", "project_data": {"campaign": {"story": "", "risks": "", "env": "", "creator_bio": ""}, "support": [], "updates": [{"status": []}], "comment_no": 4, "projec_url": "https://www.kickstarter.com/projects/1681305039/sit-eat-and-chew", "project_name": "Sit, Eat and Chew \u4e94\u5473\u6742\u9648"}}, {"backer": "Katherine Pan", "project_data": {"campaign": {"story": "", "risks": "", "env": "", "creator_bio": ""}, "support": [], "updates": [{"status": []}], "comment_no": 4, "projec_url": "https://www.kickstarter.com/projects/1057434508/borbs-cute-bird-enamel-pins", "project_name": "Borbs: Cute Bird Enamel Pins"}}, {"backer": "Katherine Pan", "project_data": {"campaign": {"story": "", "risks": "", "env": "", "creator_bio": ""}, "support": [], "updates": [{"status": []}], "comment_no": 4, "projec_url": "https://www.kickstarter.com/projects/planets/exolife-finder-a-new-telescope-to-find-life-on-exo", "project_name": "ExoLife Finder: A New Telescope To Find Life On Exoplanets"}}, {"backer": "Katherine Pan", "project_data": {"campaign": {"story": "", "risks": "", "env": "", "creator_bio": ""}, "support": [], "updates": [{"status": []}], "comment_no": 4, "projec_url": "https://www.kickstarter.com/projects/paulhausen/k-pan-the-3d-printed-panoramic-camera", "project_name": "K-Pan: the 3D Printed Panoramic Camera"}}, {"backer": "Katherine Pan", "project_data": {"campaign": {"story": "", "risks": "", "env": "", "creator_bio": ""}, "support": [], "updates": [{"status": []}], "comment_no": 4, "projec_url": "https://www.kickstarter.com/projects/wetclutch/the-dance-cartel-presents-wet-clutch", "project_name": "The Dance Cartel presents: WET CLUTCH"}}, {"backer": "Katherine Pan", "project_data": {"campaign": {"story": "", "risks": "", "env": "", "creator_bio": ""}, "support": [], "updates": [{"status": []}], "comment_no": 4, "projec_url": "https://www.kickstarter.com/projects/74147385/giving-me-life-in-the-land-of-the-deadass", "project_name": "GIVING ME LIFE (IN THE LAND OF THE DEADASS)"}}, {"backer": "Katherine Pan", "project_data": {"campaign": {"story": "", "risks": "", "env": "", "creator_bio": ""}, "support": [], "updates": [{"status": []}], "comment_no": 4, "projec_url": "https://www.kickstarter.com/projects/813138480/reptilia-solaris-enamel-pins", "project_name": "Reptilia Solaris Enamel Pins"}}, {"backer": "Katherine Pan", "project_data": {"campaign": {"story": "", "risks": "", "env": "", "creator_bio": ""}, "support": [], "updates": [{"status": []}], "comment_no": 4, "projec_url": "https://www.kickstarter.com/projects/nevadaart/trevor-paglen-orbital-reflector", "project_name": "Trevor Paglen: Orbital Reflector"}}, {"backer": "Katherine Pan", "project_data": {"campaign": {"story": "", "risks": "", "env": "", "creator_bio": ""}, "support": [], "updates": [{"status": []}], "comment_no": 4, "projec_url": "https://www.kickstarter.com/projects/1683069409/the-new-york-sorta-marathon", "project_name": "The New York Sorta Marathon"}}, {"backer": "Katherine Pan", "project_data": {"campaign": {"story": "", "risks": "", "env": "", "creator_bio": ""}, "support": [], "updates": [{"status": []}], "comment_no": 4, "projec_url": "https://www.kickstarter.com/projects/hannahpeterson/east-of-the-river", "project_name": "East of the River"}}, {"backer": "Katherine Pan", "project_data": {"campaign": {"story": "", "risks": "", "env": "", "creator_bio": ""}, "support": [], "updates": [{"status": []}], "comment_no": 4, "projec_url": "https://www.kickstarter.com/projects/whatpipeline/popel-flint-water-at-what-pipeline", "project_name": "Pope.L: Flint Water at What Pipeline"}}, {"backer": "Katherine Pan", "project_data": {"campaign": {"story": "", "risks": "", "env": "", "creator_bio": ""}, "support": [], "updates": [{"status": []}], "comment_no": 4, "projec_url": "https://www.kickstarter.com/projects/letspainttv/mission-creativity-2-earth-projects-of-earth", "project_name": "Mission Creativity 2: Earth \"Projects of Earth\""}}, {"backer": "Katherine Pan", "project_data": {"campaign": {"story": "", "risks": "", "env": "", "creator_bio": ""}, "support": [], "updates": [{"status": []}], "comment_no": 4, "projec_url": "https://www.kickstarter.com/projects/publicartfund/ai-weiwei-good-fences-make-good-neighbors", "project_name": "Ai Weiwei: Good Fences Make Good Neighbors"}}, {"backer": "Katherine Pan", "project_data": {"campaign": {"story": "", "risks": "", "env": "", "creator_bio": ""}, "support": [{"amt": "Pledge US$ 5 or more", "title": "Show your support", "descp": "Help make this book a reality by contributing $5. You'll have our heartfelt thanks.", "time": [{"ESTIMATED DELIVERY": "Sep 2017"}], "stat": ["1 backer"]}, {"amt": "Pledge US$ 20 or more", "title": "Get the ebook", "descp": "Get the ebook. The digital version of the hardcover.", "time": [{"ESTIMATED DELIVERY": "Nov 2017"}], "stat": ["20 backers"]}, {"amt": "Pledge US$ 55 or more", "title": "Get the Book", "descp": "Backers will receive a copy of the book at this level. They'll also get an acknowledgement in the back of the book.", "time": [{"ESTIMATED DELIVERY": "Dec 2017"}, {"SHIPS TO": "Anywhere in the world"}], "stat": ["77 backers"]}, {"amt": "Pledge US$ 75 or more", "title": "Get a Signed Book", "descp": "Backers will receive a signed copy of the book at this level, and an acknowledgement in the back of the book.", "time": [{"ESTIMATED DELIVERY": "Dec 2017"}, {"SHIPS TO": "Anywhere in the world"}], "stat": ["14 backers"]}, {"amt": "Pledge US$ 100 or more", "title": "Get the Book and Add UnPresidented", "descp": "This is a chance to get signed copies of the Eclipse book AND one of the few remaining, first edition copies of UnPresidented, our photo book documenting the Trump inauguration protests and Women's March. UnPresidented is out of print and is an instant collector's item. Backers will also receive an acknowledgement in the back of Chasing the Great American Eclipse.", "time": [{"ESTIMATED DELIVERY": "Dec 2017"}, {"SHIPS TO": "Anywhere in the world"}], "stat": ["18 backers", "Limited (32 left of 50)"]}, {"amt": "Pledge US$ 100 or more", "title": "Two Books", "descp": "Backers at this level will receive two copies of the book and an acknowledgement in the back of the book.\nOne for you and one as a gift!", "time": [{"ESTIMATED DELIVERY": "Dec 2017"}, {"SHIPS TO": "Anywhere in the world"}], "stat": ["2 backers"]}, {"amt": "Pledge US$ 125 or more", "title": "Get a Signed Book and 8 x 10 Art Print", "descp": "A limited number of backers will receive a signed copy of the book and an 8 x 10 art print at this level and an acknowledgement in the back of the book.", "time": [{"ESTIMATED DELIVERY": "Dec 2017"}, {"SHIPS TO": "Anywhere in the world"}], "stat": ["4 backers", "Limited (46 left of 50)"]}, {"amt": "Pledge US$ 200 or more", "title": "Signed Book and 16 x 20 Art Print", "descp": "A limited number of backers will receive a signed copy of the book and a 16 x 20 art print of an image from the book at this level and an acknowledgement in the back of the book.\nPrint will be on high-quality matte paper.", "time": [{"ESTIMATED DELIVERY": "Dec 2017"}, {"SHIPS TO": "Only certain countries"}], "stat": ["2 backers", "Limited (23 left of 25)"]}, {"amt": "Pledge US$ 500 or more", "title": "Total Eclipse Package", "descp": "A limited number of backers will receive two signed copies of the book and a SIGNED and NUMBERED 16 x 20 art print of an image from the book at this level and a special acknowledgement at the front of the list of backers.\nPrint will be on high-quality matte paper.", "time": [{"ESTIMATED DELIVERY": "Dec 2017"}, {"SHIPS TO": "Anywhere in the world"}], "stat": ["2 backers", "Limited (18 left of 20)"]}, {"amt": "Pledge US$ 35 or more", "title": "Our Launch Special", "descp": "A limited number of backers will receive a copy of the hardcover book at this level for the first 24 hours of the campaign. They'll also get an acknowledgement in the back of the book.", "time": [{"ESTIMATED DELIVERY": "Dec 2017"}, {"SHIPS TO": "Anywhere in the world"}], "stat": ["Reward no longer available", "16 backers"]}, {"amt": "Pledge US$ 45 or more", "title": "Get the Book", "descp": "A limited number of backers will receive a copy of the book at this level. They'll also get an acknowledgement in the back of the book.", "time": [{"ESTIMATED DELIVERY": "Dec 2017"}, {"SHIPS TO": "Anywhere in the world"}], "stat": ["Reward no longer available", "50 backers"]}, {"amt": "Pledge US$ 100 or more", "title": "Our Best Deal", "descp": "For the first 24 hours of the campaign, a limited number of backers will receive TWO signed copies of the book at this level, and an acknowledgement in the back of the book.\nOne for you and one as a gift!", "time": [{"ESTIMATED DELIVERY": "Dec 2017"}, {"SHIPS TO": "Anywhere in the world"}], "stat": ["Reward no longer available", "5 backers"]}], "updates": [{"status": []}], "comment_no": 48, "projec_url": "https://www.kickstarter.com/projects/focusonthestory/chasing-the-great-american-eclipse-projects-of-ear", "project_name": "Chasing the Great American Eclipse - Projects of Earth"}}, {"backer": "Katherine Pan", "project_data": {"campaign": {"story": "", "risks": "", "env": "", "creator_bio": ""}, "support": [], "updates": [{"status": []}], "comment_no": 48, "projec_url": "https://www.kickstarter.com/projects/1704591467/ant-space-the-enlightened-ant-farm", "project_name": "Ant Space: The Enlightened Ant Farm"}}, {"backer": "Katherine Pan", "project_data": {"campaign": {"story": "", "risks": "", "env": "", "creator_bio": ""}, "support": [], "updates": [{"status": []}], "comment_no": 48, "projec_url": "https://www.kickstarter.com/projects/babytattoo/dragons-are-awesome-mermaids-are-okay-too", "project_name": "Dragons vs. Mermaids (Just Kidding!)"}}, {"backer": "Katherine Pan", "project_data": {"campaign": {"story": "", "risks": "", "env": "", "creator_bio": ""}, "support": [], "updates": [{"status": []}], "comment_no": 48, "projec_url": "https://www.kickstarter.com/projects/801305394/enemy-kitchen-by-michael-rakowitz-at-mca-chicago", "project_name": "Enemy Kitchen by Michael Rakowitz at MCA Chicago"}}, {"backer": "Katherine Pan", "project_data": {"campaign": {"story": "", "risks": "", "env": "", "creator_bio": ""}, "support": [], "updates": [{"status": []}], "comment_no": 48, "projec_url": "https://www.kickstarter.com/projects/1884386802/yalla-habibi-living-with-war-in-aleppo", "project_name": "Yalla Habibi - Living with War in Aleppo"}}, {"backer": "Katherine Pan", "project_data": {"campaign": {"story": "", "risks": "", "env": "", "creator_bio": ""}, "support": [], "updates": [{"status": []}], "comment_no": 48, "projec_url": "https://www.kickstarter.com/projects/1248339799/feminisms-x-the-arab-and-muslim-diaspora", "project_name": "Feminisms x The Arab and Muslim Diaspora"}}, {"backer": "Katherine Pan", "project_data": {"campaign": {"story": "", "risks": "", "env": "", "creator_bio": ""}, "support": [], "updates": [{"status": []}], "comment_no": 48, "projec_url": "https://www.kickstarter.com/projects/aloe/aloe-app-gentle-self-care-reminders-from-yourself", "project_name": "Aloe App: Gentle self-care reminders from yourself"}}, {"backer": "Katherine Pan", "project_data": {"campaign": {"story": "", "risks": "", "env": "", "creator_bio": ""}, "support": [], "updates": [{"status": []}], "comment_no": 48, "projec_url": "https://www.kickstarter.com/projects/589123132/a-lost-cargo-aka-the-7-flaming-7", "project_name": "A Lost Cargo - aka the 7 Flaming 7"}}, {"backer": "Katherine Pan", "project_data": {"campaign": {"story": "", "risks": "", "env": "", "creator_bio": ""}, "support": [], "updates": [{"status": []}], "comment_no": 48, "projec_url": "https://www.kickstarter.com/projects/1855150928/were-still-here-an-all-trans-comics-anthology", "project_name": "We're Still Here: An All-Trans Comics Anthology"}}, {"backer": "Katherine Pan", "project_data": {"campaign": {"story": "", "risks": "", "env": "", "creator_bio": ""}, "support": [], "updates": [{"status": []}], "comment_no": 48, "projec_url": "https://www.kickstarter.com/projects/486654385/pigeon-skeleton-pin", "project_name": "Pigeon Skeleton Pin"}}, {"backer": "Katherine Pan", "project_data": {"campaign": {"story": "", "risks": "", "env": "", "creator_bio": ""}, "support": [], "updates": [{"status": []}], "comment_no": 48, "projec_url": "https://www.kickstarter.com/projects/1313520543/inside-pussy-riot", "project_name": "Inside Pussy Riot"}}]